quantum_core/__init__.py
quantum_core/document.py
quantum_core/element.py
quantum_core/style.py
quantum_core/window.py
Quantum_Core-0.0.1.dev2.dist-info/LICENSE
Quantum_Core-0.0.1.dev2.dist-info/METADATA
Quantum_Core-0.0.1.dev2.dist-info/WHEEL
Quantum_Core-0.0.1.dev2.dist-info/top_level.txt
Quantum_Core-0.0.1.dev2.dist-info/RECORD
