Metadata-Version: 2.1
Name: Quantum-Core
Version: 0.0.1.dev2
Summary: Basic Parts Of Quantum UI
Home-page: https://quantumgui.github.io
Author: Kavindu Santhusa
Author-email: kavindusanthusa@gmail.com
License: UNKNOWN
Project-URL: Bug Reports, https://github.com/quantumgui/sampleproject/issues
Project-URL: Source, https://github.com/quantumgui/sampleproject/
Keywords: basic,core,quantum,ui,gui,bom
Platform: UNKNOWN
Classifier: Development Status :: 3 - Alpha
Classifier: Intended Audience :: Developers
Classifier: Topic :: Software Development :: Build Tools
Classifier: License :: OSI Approved :: MIT License
Classifier: Programming Language :: Python :: 3
Classifier: Programming Language :: Python :: 3.5
Classifier: Programming Language :: Python :: 3.6
Classifier: Programming Language :: Python :: 3.7
Classifier: Programming Language :: Python :: 3.8
Classifier: Programming Language :: Python :: 3 :: Only
Classifier: Topic :: Software Development
Classifier: Topic :: Software Development :: User Interfaces
Classifier: Topic :: Software Development :: Widget Sets
